LICENSE
README.rst
setup.py
BLACKFORGE002/BLACKFORGE.py
BLACKFORGE002/__init__.py
BLACKFORGE002.egg-info/PKG-INFO
BLACKFORGE002.egg-info/SOURCES.txt
BLACKFORGE002.egg-info/dependency_links.txt
BLACKFORGE002.egg-info/requires.txt
BLACKFORGE002.egg-info/top_level.txt